<?xml version="1.0" encoding="utf-8" ?>
<dwsync>
<file name="bower.json" local="132679908000000000" remote="132679908000000000" testing="132679908000000000" />
<file name="daterangepicker.css" local="133258162200000000" remote="133258162200000000" testing="133258162200000000" />
<file name="daterangepicker.js" local="133258162800000000" remote="133258162800000000" testing="133258162800000000" />
<file name="drp.png" local="132679908000000000" remote="132679908000000000" testing="132679908000000000" />
<file name="moment.min.js" local="132679908000000000" remote="132679908000000000" testing="132679908000000000" />
<file name="package.js" local="132679908000000000" remote="132679908000000000" testing="132679908000000000" />
<file name="website.css" local="132679908000000000" remote="132679908000000000" testing="132679908000000000" />
<file name="website.js" local="132679908000000000" remote="132679908000000000" testing="132679908000000000" />
</dwsync>